hello_donguk777/__init__.py
hello_donguk777/hello.py
hello_DONGUK777-0.8.1.dist-info/METADATA
hello_DONGUK777-0.8.1.dist-info/WHEEL
hello_DONGUK777-0.8.1.dist-info/entry_points.txt
hello_DONGUK777-0.8.1.dist-info/top_level.txt
hello_DONGUK777-0.8.1.dist-info/RECORD
