Metadata-Version: 2.1
Name: hello_DONGUK777
Version: 0.8.1
Summary: Default template for PDM package
Author-email: DONGUK777 <kimdongyork@gmail.com>
License: MIT
Requires-Python: ==3.12.*
